{
  "root_text": {
    "uid": "sn2.23",
    "lang": "vi",
    "is_root": false,
    "title": "Serì",
    "author": "Thích Minh Châu",
    "author_short": "Minh Châu",
    "author_uid": "minh_chau",
    "next": {
      "author_uid": "minh_chau",
      "lang": "vi",
      "name": "With Ghaṭīkāra ",
      "uid": "sn2.24"
    },
    "previous": {
      "author_uid": "minh_chau",
      "lang": "vi",
      "name": "With Khema ",
      "uid": "sn2.22"
    },
    "text": "<!DOCTYPE html>\n<html>\n<head>\n<meta charset='UTF-8'>\n<meta name='author' content='Thích Minh Châu'>\n<title></title>\n</head>\n<body>\n<article id='sn2.23' lang='vi'>\n<header>\n<ul>\n<li class='division'>Chương 2: Tương Ưng Thiên Tử</li>\n<li>III: Phẩm Các Ngoại Ðạo</li>\n</ul>\n<h1>2.23. Serì</h1>\n</header>\n<p><a class='pts' id='S.i.57' href='#S.i.57'></a><a class='ref vi-n' id='vi-n1' href='#vi-n1'>Vi-n 1</a> Ðứng một bên, Thiên tử Serì nói lên bài kệ với Thế Tôn:</p>\n<blockquote class='gatha'>\n<p>Cả hai loại Trời, Người,<br>\nÐều ưa thích ăn uống,<br>\nCó Dạ-xoa tên nào,<br>\nLại không thích ăn uống!</p>\n<span class='speaker'>(Thế Tôn)</span>\n<p>Ai cho với lòng tin,<br>\nVới tâm tư thanh tịnh,<br>\nÐược phần món ăn ấy,<br>\nÐời này và đời sau.<br>\nVậy hãy ngăn xan tham,<br>\nBố thí, nhiếp cấu uế,<br>\nChúng sanh vẫn hưởng thọ,<br>\nCông đức trong đời sau.</p>\n</blockquote>\n<p><a class='ref vi-n' id='vi-n2' href='#vi-n2'>Vi-n 2</a> —Thật là hy hữu, bạch Thế Tôn! Thật là kỳ diệu, bạch Thế Tôn! Thế Tôn đã nói điều khéo nói như vậy:</p>\n<blockquote class='gatha'>\n<p>“Ai cho với lòng tin,<br>\nVới tâm tư thanh tịnh,<br>\nÐược phần món ăn ấy,<br>\nÐời này và đời sau.<br>\nVậy hãy ngăn xan tham,<br>\nBố thí, nhiếp cấu uế,<br>\nChúng sanh vẫn hưởng thọ,<br>\nCông đức trong đời sau.”</p>\n</blockquote>\n<p><a class='ref vi-n' id='vi-n3' href='#vi-n3'>Vi-n 3</a> Bạch Thế Tôn, thuở xưa con là vị vua tên Serì ưa bố thí, là bậc thí chủ tán thán bố thí. Bạch Thế Tôn, tại bốn cửa thành, bố thí được phân phát nhân danh con, cho những ai đến xin, cho các vị Bà-la-môn và Sa-môn, cho các người nghèo đói và tàn phế, cho các nhà lữ hành và hành khất.</p>\n<p><a class='ref vi-n' id='vi-n4' href='#vi-n4'>Vi-n 4</a> Bạch Thế Tôn, khi con đến các cung phi của con, họ thưa với con: “Ðại vương thường hay bố thí, còn chúng con chưa bố thí. Lành thay nếu chúng con được nương tựa Ðại vương để bố thí và làm các công đức.”</p>\n<p><a class='ref vi-n' id='vi-n5' href='#vi-n5'>Vi-n 5</a> Bạch Thế Tôn, con suy nghĩ như sau: “Ta là người ưa bố thí, là thí chủ tán thán bố thí. Nay ta phải trả lời như thế nào khi họ đến và thưa: ‘Chúng ta hãy bố thí'?”. Bạch Thế Tôn, con cho các cung phi cửa thành thứ nhất. Ở đây các cung phi được bố thí, và bố thí của con trở lui lại cho con.</p>\n<p><a class='ref vi-n' id='vi-n6' href='#vi-n6'>Vi-n 6</a> Rồi bạch Thế Tôn, các Sát-đế-lỵ (Khattiya) chư hầu của con đến con và thưa: “Ðại vương đã bố thí. Các cung phi đã bố thí. Chúng con chưa bố thí. Lành thay nếu chúng con được nương tựa Ðại vương để bố thí và làm các công đức”.</p>\n<p>Bạch Thế Tôn, con suy nghĩ như sau: “Ta là người ưa bố thí, là thí chủ tán thán bố thí. Nay ta phải trả lời như thế nào khi họ đến và thưa: “Chúng ta hãy bố thí”?”. Bạch Thế Tôn, con cho các chư hầu Khattiya cửa thành thứ hai. Ở đây các chư hầu Khattiya được bố thí, và bố thí của con được trở lui lại cho con.</p>\n<p><a class='ref vi-n' id='vi-n7' href='#vi-n7'>Vi-n 7</a> Rồi bạch Thế Tôn, quân đội đến con và thưa: “Ðại vương đã bố thí. Các cung phi đã bố thí. Các chư hầu Khattiya đã bố thí. Chúng con chưa bố thí. Tốt lành thay nếu chúng con được nương tựa Ðại vương để bố thí và làm các công đức”.</p>\n<p>Bạch Thế Tôn, con suy nghĩ như sau: “Ta là người ưa bố thí, là thí chủ tán thán bố thí. Nay ta phải trả lời như thế nào khi họ đến và thưa: “Chúng ta hãy bố thí”?”. Bạch Thế Tôn, con cho quân đội cửa thành thứ ba. Ở đây quân đội được bố thí và bố thí của con được trở lui lại cho con.</p>\n<p><a class='ref vi-n' id='vi-n8' href='#vi-n8'>Vi-n 8</a> Rồi bạch Thế Tôn, các Bà-la-môn gia chủ đến con và thưa: “Ðại vương đã bố thí. Các cung phi đã bố thí. Các chư hầu Khattiya đã bố thí. Quân đội đã bố thí. Chúng con chưa bố thí. Tốt lành thay nếu chúng con được nương tựa Ðại vương để bố thí và làm các công đức!”.</p>\n<p>Bạch Thế Tôn, con suy nghĩ như sau: “Ta là người ưa bố thí, là thí chủ tán thán bố thí. Nay ta phải trả lời như thế nào khi họ đến và thưa: “Chúng ta hãy bố thí”?”. Bạch Thế Tôn, con cho các Bà-la-môn gia chủ cửa thành thứ tư. Ở đây các Bà-la-môn gia chủ được bố thí và bố thí của con được trở lui lại cho con.</p>\n<p><a class='ref vi-n' id='vi-n9' href='#vi-n9'>Vi-n 9</a> Rồi bạch Thế Tôn, các người của con đến con và thưa: “Nay Ðại vương không còn bố thí nào để cho nữa”.</p>\n<p>Khi được nói vậy, bạch Thế Tôn, con nói với các người ấy như sau: “Này các Ông, các thuế má thâu hoạch được từ các nước ngoài vào, một nửa hãy gửi vào trong nội thành, một nửa ngay tại chỗ ấy đem bố thí cho các vị Sa-môn, Bà-la-môn, các người nghèo và tàn tật, các nhà lữ hành và hành khất”.</p>\n<p><a class='ref vi-n' id='vi-n10' href='#vi-n10'>Vi-n 10</a> Như vậy, bạch Thế Tôn, con không chấm dứt trong một thời gian dài các việc làm công đức, trong một thời gian dài các việc làm thiện, những việc làm được con xem như là công đức, hay như là công đức quả hay như là những điều kiện được sanh thiên giới.</p>\n<p><a class='ref vi-n' id='vi-n11' href='#vi-n11'>Vi-n 11</a> Thật là hy hữu, bạch Thế Tôn! Thật là kỳ diệu, bạch Thế Tôn! Thế Tôn đã nói lên điều khéo nói như vầy:</p>\n<blockquote class='gatha'>\n<p>“Ai cho với lòng tin,<br>\nVới tâm tư thanh tịnh,<br>\nÐược phần món ăn ấy,<br>\nÐời này và đời sau.<br>\nVậy hãy ngăn xan tham,<br>\nBố thí, nhiếp cấu uế,<br>\nChúng sanh vẫn hưởng thọ,<br>\nCông đức trong đời sau.”</p>\n</blockquote>\n<footer>\n<p>Bộ kinh đã được <span class='author'>Hòa thượng Thích Minh Châu</span> dịch sang Việt ngữ và Thiền viện Vạn Hạnh phát hành trong đầu thập niên <span class='publication-date'>1980</span>. Sau đó, trong chương trình phiên dịch và ấn hành Ðại tạng kinh Việt Nam, bộ kinh được tái bản năm 1993 và có số thứ tự từ 12 đến 16.</p>\n<p>Prepared for SuttaCentral by <span class='editor'>Blake Walsh</span>.</p>\n</footer>\n</article>\n</body>\n</html>\n"
  },
  "translation": {
    "uid": "sn2.23",
    "lang": "vi",
    "is_root": false,
    "title": "Serì",
    "author": "Thích Minh Châu",
    "author_short": "Minh Châu",
    "author_uid": "minh_chau",
    "next": {
      "author_uid": "minh_chau",
      "lang": "vi",
      "name": "With Ghaṭīkāra ",
      "uid": "sn2.24"
    },
    "previous": {
      "author_uid": "minh_chau",
      "lang": "vi",
      "name": "With Khema ",
      "uid": "sn2.22"
    },
    "text": "<!DOCTYPE html>\n<html>\n<head>\n<meta charset='UTF-8'>\n<meta name='author' content='Thích Minh Châu'>\n<title></title>\n</head>\n<body>\n<article id='sn2.23' lang='vi'>\n<header>\n<ul>\n<li class='division'>Chương 2: Tương Ưng Thiên Tử</li>\n<li>III: Phẩm Các Ngoại Ðạo</li>\n</ul>\n<h1>2.23. Serì</h1>\n</header>\n<p><a class='pts' id='S.i.57' href='#S.i.57'></a><a class='ref vi-n' id='vi-n1' href='#vi-n1'>Vi-n 1</a> Ðứng một bên, Thiên tử Serì nói lên bài kệ với Thế Tôn:</p>\n<blockquote class='gatha'>\n<p>Cả hai loại Trời, Người,<br>\nÐều ưa thích ăn uống,<br>\nCó Dạ-xoa tên nào,<br>\nLại không thích ăn uống!</p>\n<span class='speaker'>(Thế Tôn)</span>\n<p>Ai cho với lòng tin,<br>\nVới tâm tư thanh tịnh,<br>\nÐược phần món ăn ấy,<br>\nÐời này và đời sau.<br>\nVậy hãy ngăn xan tham,<br>\nBố thí, nhiếp cấu uế,<br>\nChúng sanh vẫn hưởng thọ,<br>\nCông đức trong đời sau.</p>\n</blockquote>\n<p><a class='ref vi-n' id='vi-n2' href='#vi-n2'>Vi-n 2</a> —Thật là hy hữu, bạch Thế Tôn! Thật là kỳ diệu, bạch Thế Tôn! Thế Tôn đã nói điều khéo nói như vậy:</p>\n<blockquote class='gatha'>\n<p>“Ai cho với lòng tin,<br>\nVới tâm tư thanh tịnh,<br>\nÐược phần món ăn ấy,<br>\nÐời này và đời sau.<br>\nVậy hãy ngăn xan tham,<br>\nBố thí, nhiếp cấu uế,<br>\nChúng sanh vẫn hưởng thọ,<br>\nCông đức trong đời sau.”</p>\n</blockquote>\n<p><a class='ref vi-n' id='vi-n3' href='#vi-n3'>Vi-n 3</a> Bạch Thế Tôn, thuở xưa con là vị vua tên Serì ưa bố thí, là bậc thí chủ tán thán bố thí. Bạch Thế Tôn, tại bốn cửa thành, bố thí được phân phát nhân danh con, cho những ai đến xin, cho các vị Bà-la-môn và Sa-môn, cho các người nghèo đói và tàn phế, cho các nhà lữ hành và hành khất.</p>\n<p><a class='ref vi-n' id='vi-n4' href='#vi-n4'>Vi-n 4</a> Bạch Thế Tôn, khi con đến các cung phi của con, họ thưa với con: “Ðại vương thường hay bố thí, còn chúng con chưa bố thí. Lành thay nếu chúng con được nương tựa Ðại vương để bố thí và làm các công đức.”</p>\n<p><a class='ref vi-n' id='vi-n5' href='#vi-n5'>Vi-n 5</a> Bạch Thế Tôn, con suy nghĩ như sau: “Ta là người ưa bố thí, là thí chủ tán thán bố thí. Nay ta phải trả lời như thế nào khi họ đến và thưa: ‘Chúng ta hãy bố thí'?”. Bạch Thế Tôn, con cho các cung phi cửa thành thứ nhất. Ở đây các cung phi được bố thí, và bố thí của con trở lui lại cho con.</p>\n<p><a class='ref vi-n' id='vi-n6' href='#vi-n6'>Vi-n 6</a> Rồi bạch Thế Tôn, các Sát-đế-lỵ (Khattiya) chư hầu của con đến con và thưa: “Ðại vương đã bố thí. Các cung phi đã bố thí. Chúng con chưa bố thí. Lành thay nếu chúng con được nương tựa Ðại vương để bố thí và làm các công đức”.</p>\n<p>Bạch Thế Tôn, con suy nghĩ như sau: “Ta là người ưa bố thí, là thí chủ tán thán bố thí. Nay ta phải trả lời như thế nào khi họ đến và thưa: “Chúng ta hãy bố thí”?”. Bạch Thế Tôn, con cho các chư hầu Khattiya cửa thành thứ hai. Ở đây các chư hầu Khattiya được bố thí, và bố thí của con được trở lui lại cho con.</p>\n<p><a class='ref vi-n' id='vi-n7' href='#vi-n7'>Vi-n 7</a> Rồi bạch Thế Tôn, quân đội đến con và thưa: “Ðại vương đã bố thí. Các cung phi đã bố thí. Các chư hầu Khattiya đã bố thí. Chúng con chưa bố thí. Tốt lành thay nếu chúng con được nương tựa Ðại vương để bố thí và làm các công đức”.</p>\n<p>Bạch Thế Tôn, con suy nghĩ như sau: “Ta là người ưa bố thí, là thí chủ tán thán bố thí. Nay ta phải trả lời như thế nào khi họ đến và thưa: “Chúng ta hãy bố thí”?”. Bạch Thế Tôn, con cho quân đội cửa thành thứ ba. Ở đây quân đội được bố thí và bố thí của con được trở lui lại cho con.</p>\n<p><a class='ref vi-n' id='vi-n8' href='#vi-n8'>Vi-n 8</a> Rồi bạch Thế Tôn, các Bà-la-môn gia chủ đến con và thưa: “Ðại vương đã bố thí. Các cung phi đã bố thí. Các chư hầu Khattiya đã bố thí. Quân đội đã bố thí. Chúng con chưa bố thí. Tốt lành thay nếu chúng con được nương tựa Ðại vương để bố thí và làm các công đức!”.</p>\n<p>Bạch Thế Tôn, con suy nghĩ như sau: “Ta là người ưa bố thí, là thí chủ tán thán bố thí. Nay ta phải trả lời như thế nào khi họ đến và thưa: “Chúng ta hãy bố thí”?”. Bạch Thế Tôn, con cho các Bà-la-môn gia chủ cửa thành thứ tư. Ở đây các Bà-la-môn gia chủ được bố thí và bố thí của con được trở lui lại cho con.</p>\n<p><a class='ref vi-n' id='vi-n9' href='#vi-n9'>Vi-n 9</a> Rồi bạch Thế Tôn, các người của con đến con và thưa: “Nay Ðại vương không còn bố thí nào để cho nữa”.</p>\n<p>Khi được nói vậy, bạch Thế Tôn, con nói với các người ấy như sau: “Này các Ông, các thuế má thâu hoạch được từ các nước ngoài vào, một nửa hãy gửi vào trong nội thành, một nửa ngay tại chỗ ấy đem bố thí cho các vị Sa-môn, Bà-la-môn, các người nghèo và tàn tật, các nhà lữ hành và hành khất”.</p>\n<p><a class='ref vi-n' id='vi-n10' href='#vi-n10'>Vi-n 10</a> Như vậy, bạch Thế Tôn, con không chấm dứt trong một thời gian dài các việc làm công đức, trong một thời gian dài các việc làm thiện, những việc làm được con xem như là công đức, hay như là công đức quả hay như là những điều kiện được sanh thiên giới.</p>\n<p><a class='ref vi-n' id='vi-n11' href='#vi-n11'>Vi-n 11</a> Thật là hy hữu, bạch Thế Tôn! Thật là kỳ diệu, bạch Thế Tôn! Thế Tôn đã nói lên điều khéo nói như vầy:</p>\n<blockquote class='gatha'>\n<p>“Ai cho với lòng tin,<br>\nVới tâm tư thanh tịnh,<br>\nÐược phần món ăn ấy,<br>\nÐời này và đời sau.<br>\nVậy hãy ngăn xan tham,<br>\nBố thí, nhiếp cấu uế,<br>\nChúng sanh vẫn hưởng thọ,<br>\nCông đức trong đời sau.”</p>\n</blockquote>\n<footer>\n<p>Bộ kinh đã được <span class='author'>Hòa thượng Thích Minh Châu</span> dịch sang Việt ngữ và Thiền viện Vạn Hạnh phát hành trong đầu thập niên <span class='publication-date'>1980</span>. Sau đó, trong chương trình phiên dịch và ấn hành Ðại tạng kinh Việt Nam, bộ kinh được tái bản năm 1993 và có số thứ tự từ 12 đến 16.</p>\n<p>Prepared for SuttaCentral by <span class='editor'>Blake Walsh</span>.</p>\n</footer>\n</article>\n</body>\n</html>\n"
  },
  "segmented": false,
  "suttaplex": {
    "acronym": "SN 2.23",
    "volpages": " PTS (1st ed) 1.58, PTS (1st ed) 1.59",
    "alt_volpages": " PTS (2nd ed) 1.133, PTS (2nd ed) 1.134, PTS (2nd ed) 1.135, PTS (2nd ed) 1.136, PTS (2nd ed) 1.137",
    "uid": "sn2.23",
    "blurb": "The deity Serī speaks of how everyone loves food., to which the Buddha responds with verses in praise of giving. Serī speaks of his own generosity in a past life.",
    "difficulty": null,
    "original_title": "Serīsutta",
    "root_lang": "pli",
    "root_lang_name": "Pāli",
    "type": "leaf",
    "from": null,
    "translated_title": "Serì",
    "translations": [
      {
        "lang": "de",
        "lang_name": "Deutsch",
        "is_root": false,
        "author": "Sabbamitta",
        "author_short": "sabbamitta",
        "author_uid": "sabbamitta",
        "publication_date": "2019",
        "id": "sn2.23_translation-de-sabbamitta",
        "segmented": true,
        "title": "Mit Serī ",
        "volpage": null,
        "has_comment": false
      },
      {
        "lang": "en",
        "lang_name": "English",
        "is_root": false,
        "author": "Bhikkhu Sujato",
        "author_short": "sujato",
        "author_uid": "sujato",
        "publication_date": "2018",
        "id": "sn2.23_translation-en-sujato",
        "segmented": true,
        "title": "With Serī ",
        "volpage": null,
        "has_comment": true
      },
      {
        "lang": "it",
        "lang_name": "Italiano",
        "is_root": false,
        "author": "Giovanni Zappa",
        "author_short": "giovannizappa",
        "author_uid": "giovannizappa",
        "publication_date": "2025",
        "id": "sn2.23_translation-it-giovannizappa",
        "segmented": true,
        "title": "Il discorso con Serī ",
        "volpage": null,
        "has_comment": false
      },
      {
        "lang": "pli",
        "lang_name": "Pāli",
        "is_root": true,
        "author": "Mahāsaṅgīti Tipiṭaka Buddhavasse 2500",
        "author_short": "ms",
        "author_uid": "ms",
        "publication_date": null,
        "id": "sn2.23_root-pli-ms",
        "segmented": true,
        "title": null,
        "volpage": null,
        "has_comment": false
      },
      {
        "lang": "pt",
        "lang_name": "Português",
        "is_root": false,
        "author": "Laera et al.",
        "author_short": "laera",
        "author_uid": "laera",
        "publication_date": null,
        "id": "sn2.23_translation-pt-laera-quaresma",
        "segmented": true,
        "title": "Com Seri",
        "volpage": null,
        "has_comment": false
      },
      {
        "lang": "ru",
        "lang_name": "Русский",
        "is_root": false,
        "author": "SV theravada.ru",
        "author_short": "sv",
        "author_uid": "sv",
        "publication_date": "2024",
        "id": "sn2.23_translation-ru-sv",
        "segmented": true,
        "title": "Сери ",
        "volpage": null,
        "has_comment": false
      },
      {
        "lang": "sr",
        "lang_name": "Srpski",
        "is_root": false,
        "author": "Branislav Kovačević",
        "author_short": "brankokovacevic",
        "author_uid": "brankokovacevic",
        "publication_date": "2023",
        "id": "sn2.23_translation-sr-brankokovacevic",
        "segmented": true,
        "title": "Serī ",
        "volpage": null,
        "has_comment": false
      },
      {
        "lang": "bn",
        "lang_name": "বাংলা",
        "is_root": false,
        "author": "ইন্দ্রগুপ্ত ভিক্ষু, বঙ্গীস ভিক্ষু, অজিত ভিক্ষু, সীবক ভিক্ষু",
        "author_short": "ইন্দ্রগুপ্ত …",
        "author_uid": "indragupta-bangish-ajit-sivak",
        "publication_date": "2018",
        "id": "bn_sn2.23_indragupta-bangish-ajit-sivak",
        "segmented": false,
        "volpage": null,
        "has_comment": false
      },
      {
        "lang": "ca",
        "lang_name": "Català",
        "is_root": false,
        "author": "Albert Biayna Gea",
        "author_short": "Gea",
        "author_uid": "gea",
        "publication_date": null,
        "id": "ca_sn2.23_gea",
        "segmented": false,
        "volpage": null,
        "has_comment": false
      },
      {
        "lang": "de",
        "lang_name": "Deutsch",
        "is_root": false,
        "author": "Wilhelm Geiger",
        "author_short": "Geiger",
        "author_uid": "geiger",
        "publication_date": "1925",
        "id": "de_sn2.23_geiger",
        "segmented": false,
        "volpage": null,
        "has_comment": false
      },
      {
        "lang": "es",
        "lang_name": "Español",
        "is_root": false,
        "author": "Anton P. Baron",
        "author_short": "Baron",
        "author_uid": "baron",
        "publication_date": "2015",
        "id": "es_sn2.23_baron",
        "segmented": false,
        "volpage": null,
        "has_comment": false
      },
      {
        "lang": "id",
        "lang_name": "Bahasa Indonesia",
        "is_root": false,
        "author": "Indra Anggara",
        "author_short": "Anggara",
        "author_uid": "anggara",
        "publication_date": null,
        "id": "id_sn2.23_anggara",
        "segmented": false,
        "volpage": null,
        "has_comment": false
      },
      {
        "lang": "it",
        "lang_name": "Italiano",
        "is_root": false,
        "author": "Enzo Alfano",
        "author_short": "Alfano",
        "author_uid": "alfano",
        "publication_date": null,
        "id": "it_sn2.23_alfano",
        "segmented": false,
        "volpage": null,
        "has_comment": false
      },
      {
        "lang": "jpn",
        "lang_name": "日本語",
        "is_root": false,
        "author": "関西パーリ語実習会",
        "author_short": "関西パーリ語実習会",
        "author_uid": "kansai",
        "publication_date": "2023",
        "id": "jpn_sn2.23_kansai",
        "segmented": false,
        "volpage": null,
        "has_comment": false
      },
      {
        "lang": "my",
        "lang_name": "မြန်မာဘာသာ",
        "is_root": false,
        "author": "Pitaka Myanmar Translation",
        "author_short": "PMT",
        "author_uid": "pmt",
        "publication_date": null,
        "id": "my_sn2.23_pmt",
        "segmented": false,
        "volpage": null,
        "has_comment": false
      },
      {
        "lang": "no",
        "lang_name": "Norsk",
        "is_root": false,
        "author": "Kåre A. Lie",
        "author_short": "Lie",
        "author_uid": "lie",
        "publication_date": "2015",
        "id": "no_sn2.23_lie",
        "segmented": false,
        "volpage": null,
        "has_comment": false
      },
      {
        "lang": "ru",
        "lang_name": "Русский",
        "is_root": false,
        "author": "SV",
        "author_short": "SV",
        "author_uid": "sv",
        "publication_date": "2015",
        "id": "ru_sn2.23_sv",
        "segmented": false,
        "volpage": null,
        "has_comment": false
      },
      {
        "lang": "si",
        "lang_name": "සිංහල",
        "is_root": false,
        "author": "A.P. de Zoysa",
        "author_short": "Zoysa",
        "author_uid": "zoysa",
        "publication_date": null,
        "id": "si_sn2.23_zoysa",
        "segmented": false,
        "volpage": null,
        "has_comment": false
      },
      {
        "lang": "th",
        "lang_name": "ไทย",
        "is_root": false,
        "author": "Siam Rath",
        "author_short": "Siam Rath",
        "author_uid": "siam_rath",
        "publication_date": null,
        "id": "th_sn2.23_siam_rath",
        "segmented": false,
        "volpage": null,
        "has_comment": false
      },
      {
        "author": "Thích Minh Châu",
        "author_short": "Minh Châu",
        "author_uid": "minh_chau",
        "has_comment": false,
        "id": "vi_sn2.23_minh_chau",
        "is_root": false,
        "lang": "vi",
        "lang_name": "Tiếng Việt",
        "publication_date": "1980",
        "segmented": false,
        "volpage": null,
        "title": "Serì"
      },
      {
        "lang": "zh",
        "lang_name": "汉语",
        "is_root": false,
        "author": "莊春江",
        "author_short": "莊春江",
        "author_uid": "zhuang",
        "publication_date": null,
        "id": "zh_sn2.23_zhuang",
        "segmented": false,
        "volpage": null,
        "has_comment": false
      }
    ],
    "parallel_count": 17,
    "biblio": null,
    "priority_author_uid": null,
    "verseNo": "ms12S1_494, msdiv104,csp1ed12.57, csp2ed12.57, dr15.78, ms12S1_495, pts-vp-pli2ed1.133,ms12S1_496,ms12S1_497, ndp12.56,ms12S1_498, pts-vp-pli1ed1.58,bj13.112, cck15.78, ms12S1_499,ms12S1_500, pts-vp-pli2ed1.134,dr15.79, ms12S1_501, sya15.83,cck15.79, csp1ed12.58, csp2ed12.58, ms12S1_502, pts-vp-pli2ed1.135, vri23.72,ms12S1_503, ndp12.57, pts-vp-pli1ed1.59, sya15.84,cck15.80, dr15.80, ms12S1_504, pts-vp-pli2ed1.136,bj13.114, ms12S1_505, pts-vp-pli2ed1.137, vri23.73,ms12S1_506, sya15.85,ms12S1_507",
    "previous": {
      "name": null,
      "uid": null
    },
    "next": {
      "name": null,
      "uid": null
    }
  },
  "bilara_root_text": {
    "uid": "sn2.23",
    "author": "Mahāsaṅgīti Tipiṭaka Buddhavasse 2500",
    "author_short": "ms",
    "author_uid": "ms",
    "lang": "pli",
    "title": "Serīsutta",
    "previous": {
      "author_uid": "ms",
      "lang": "pli",
      "name": null,
      "uid": null
    },
    "next": {
      "author_uid": "ms",
      "lang": "pli",
      "name": null,
      "uid": null
    }
  },
  "bilara_translated_text": null,
  "candidate_authors": [
    "sujato"
  ]
}