{
  "html_text": {
    "an6.76:0.1": "<article id='an6.76'><header><ul><li class='division'>{}</li>",
    "an6.76:0.2": "<li>{}</li></ul>",
    "an6.76:0.3": "<h1 class='sutta-title'>{}</h1></header>",
    "an6.76:1.1": "<p>{}",
    "an6.76:1.2": "{}",
    "an6.76:1.3": "{}",
    "an6.76:1.4": "{}</p>",
    "an6.76:2.1": "<p>{}",
    "an6.76:2.2": "{}",
    "an6.76:2.3": "{}",
    "an6.76:2.4": "{}</p>",
    "an6.76:2.5": "<p class='endsutta'>{}</p></article>"
  },
  "root_text": {
    "an6.76:0.1": "Aṅguttara Nikāya 6.76 ",
    "an6.76:0.2": "8. Arahattavagga ",
    "an6.76:0.3": "Arahattasutta ",
    "an6.76:1.1": "“Cha, bhikkhave, dhamme appahāya abhabbo arahattaṁ sacchikātuṁ. ",
    "an6.76:1.2": "Katame cha? ",
    "an6.76:1.3": "Mānaṁ, omānaṁ, atimānaṁ, adhimānaṁ, thambhaṁ, atinipātaṁ. ",
    "an6.76:1.4": "Ime kho, bhikkhave, cha dhamme appahāya abhabbo arahattaṁ sacchikātuṁ. ",
    "an6.76:2.1": "Cha, bhikkhave, dhamme pahāya bhabbo arahattaṁ sacchikātuṁ. ",
    "an6.76:2.2": "Katame cha? ",
    "an6.76:2.3": "Mānaṁ, omānaṁ, atimānaṁ, adhimānaṁ, thambhaṁ, atinipātaṁ. ",
    "an6.76:2.4": "Ime kho, bhikkhave, cha dhamme pahāya bhabbo arahattaṁ sacchikātun”ti. ",
    "an6.76:2.5": "Dutiyaṁ. "
  },
  "translation_text": {
    "an6.76:0.1": "Numbered Discourses 6.76 ",
    "an6.76:0.2": "8. Perfection ",
    "an6.76:0.3": "Perfection ",
    "an6.76:1.1": "“Mendicants, without giving up six things you can’t realize perfection. ",
    "an6.76:1.2": "What six? ",
    "an6.76:1.3": "Conceit, inferiority complex, superiority complex, overestimation, obstinacy, and groveling. ",
    "an6.76:1.4": "Without giving up these six qualities you can’t realize perfection. ",
    "an6.76:2.1": "After giving up six things you can realize perfection. ",
    "an6.76:2.2": "What six? ",
    "an6.76:2.3": "Conceit, inferiority complex, superiority complex, overestimation, obstinacy, and groveling. ",
    "an6.76:2.4": "After giving up these six things you can realize perfection.” "
  },
  "reference_text": {
    "an6.76:1.1": "ms16A6_656, msdiv76, pts-vp-pli3.430",
    "an6.76:2.1": "dr22.466, ms16A6_657, vri38.132"
  },
  "keys_order": [
    "an6.76:0.1",
    "an6.76:0.2",
    "an6.76:0.3",
    "an6.76:1.1",
    "an6.76:1.2",
    "an6.76:1.3",
    "an6.76:1.4",
    "an6.76:2.1",
    "an6.76:2.2",
    "an6.76:2.3",
    "an6.76:2.4",
    "an6.76:2.5"
  ]
}