{
  "root_text": {
    "uid": "mn17",
    "lang": "vi",
    "is_root": false,
    "title": "Kinh Khu rừng",
    "author": "Thích Minh Châu",
    "author_short": "Minh Châu",
    "author_uid": "minh_chau",
    "next": {
      "author_uid": "minh_chau",
      "lang": "vi",
      "name": "The Honey-Cake ",
      "uid": "mn18"
    },
    "previous": {
      "author_uid": "minh_chau",
      "lang": "vi",
      "name": "Emotional Barrenness ",
      "uid": "mn16"
    },
    "text": "<!DOCTYPE html>\n<html>\n<head>\n<meta charset='UTF-8'>\n<meta name='author' content='Thích Minh Châu'>\n<title></title>\n</head>\n<body>\n<article id='mn17' lang='vi'>\n<header>\n<ul>\n<li class='nikaya'>Trung Bộ Kinh</li>\n</ul>\n<h1 class='sutta'>17. Kinh Khu rừng</h1>\n</header>\n<p>Tôi nghe như vầy:</p>\n<p><a class='ref sc' id='sc1' href='#sc1'>SC 1</a>Một thời, Thế Tôn ở <i lang='pli' translate='no'>Sāvatthi</i> (Xá-vệ), tại <i lang='pli' translate='no'>Jetavana</i> (Kỳ-đà Lâm), vườn ông <i lang='pli' translate='no'>Anāthapiṇḍika</i> (Cấp Cô Ðộc). Ở đây, Thế Tôn gọi các Tỷ-kheo: “Này các Tỷ-kheo”. “Bạch Thế Tôn”, các Tỷ-kheo ấy vâng đáp Thế Tôn. Thế Tôn nói như sau: “Chư Tỷ-kheo, Ta sẽ giảng cho các Người pháp môn về khu rừng. Hãy nghe và suy nghiệm kỹ, Ta sẽ giảng”.:” Thưa vâng, bạch Thế Tôn”. Những Tỷ-kheo ấy vâng đáp Thế Tôn. Thế Tôn thuyết giảng như sau</p>\n<p><a class='ref sc' id='sc2' href='#sc2'>SC 2</a>—Chư Tỷ-kheo, ở đây, Tỷ-kheo sống tại một khu rừng nào. Tỷ-kheo sống tại khu rừng này, các niệm chưa được an trú không được an trú, tâm tư chưa được định tĩnh không được định tĩnh, các lậu hoặc chưa được hoàn toàn đoạn trừ không được hoàn toàn đoạn trừ, vô thượng an ổn khỏi các ách phược chưa được chứng đạt không được chứng đạt, và những vật dụng này cần thiết cho đời sống mà một người xuất gia cần phải sắm đủ, như y phục, đồ ăn khất thực, sàng tọa, y dược trị bệnh, những vật dụng này kiếm được một cách khó khăn. Chư Tỷ-kheo, Tỷ-kheo ấy cần phải suy nghĩ: “Ta sống tại khu rừng này. Khi ta sống tại khu rừng này, các niệm chưa được an trú không được an trú, tâm tư chưa được định tĩnh không được định tĩnh, các lậu hoặc chưa được hoàn toàn đoạn trừ không được hoàn toàn đoạn trừ, vô thượng an ổn khỏi các ách phược chưa được chứng đạt không được chứng đạt, và những vật dụng cần thiết cho đời sống mà một vị xuất gia cần phải sắm đủ, như y phục, đồ ăn khất thực, sàng tọa, dược phẩm trị bệnh, những vật dụng này kiếm được một cách khó khăn”. Này các Tỷ-kheo, Tỷ-kheo ấy phải từ bỏ ngôi rừng ấy, không được ở lại, ngay lúc ban ngày hay lúc ban đêm.</p>\n<p><a class='ref sc' id='sc3' href='#sc3'>SC 3</a>Chư Tỷ-kheo, ở đây, Tỷ-kheo sống tại một khu rừng nào. Tỷ-kheo sống tại khu rừng này, các niệm chưa được an trú không được an trú, tâm tư chưa được định tĩnh không được định tĩnh, các lậu hoặc chưa được hoàn toàn đoạn trừ không được hoàn toàn đoạn trừ, vô thượng an ổn khỏi các ách phược chưa được chứng đạt không được chứng đạt, và những vật dụng cần thiết cho đời sống mà một người xuất gia cần phải sắm đủ, như y phục, đồ ăn khất thực, sàng tọa, dược phẩm trị bệnh, những vật dụng này kiếm được một cách không khó khăn. Chư Tỷ-kheo, Tỷ-kheo ấy cần phải suy nghĩ như sau: “Ta sống tại khu rừng này. Khi ta sống tại khu rừng này, các niệm chưa được an trú không được an trú … những vật dụng này kiếm được một cách không khó khăn. Nhưng không phải vì y phục mà ta xuất gia, từ bỏ gia đình sống không gia đình, không phải vì đồ ăn khất thực … không phải vì sàng tọa … không phải vì dược phẩm trị bệnh mà ta xuất gia, từ bỏ gia đình, sống không gia đình. Nhưng trong khi ta ở tại khu rừng này, các niệm chưa được an trú không được an trú … vô thượng an ổn khỏi các ách phược chưa được chứng đạt không được chứng đạt”. Này các Tỷ-kheo, Tỷ-kheo ấy chỉ với suy tính này, phải từ bỏ ngôi rừng ấy, không được ở lại.</p>\n<p><a class='ref sc' id='sc4' href='#sc4'>SC 4</a>Chư Tỷ-kheo, ở đây, Tỷ-kheo sống tại một khu rừng nào. Tỷ-kheo sống tại khu rừng này, các niệm chưa được an trú được an trú, tâm tư chưa được định tĩnh được định tĩnh; các lậu hoặc chưa được hoàn toàn đoạn trừ được hoàn toàn đoạn trừ, vô thượng an ổn khỏi các ách phược chưa được chứng đạt được chứng đạt, nhưng những vật dụng cần thiết cho đời sống một người xuất gia cần phải sắm đủ, như y phục, đồ ăn khất thực, sàng tọa, dược phẩm trị bệnh, những vật này kiếm được một cách khó khăn. Chư Tỷ-kheo, Tỷ-kheo ấy cần phải suy nghĩ như sau: “Ta sống tại khu rừng này. Khi ta sống tại khu rừng này, các niệm chưa được an trú được an trú … vô thượng an ổn khỏi các ách phược chưa được chứng đạt được chứng đạt … những vật dụng này kiếm được một cách khó khăn. Nhưng không phải vì y phục mà ta xuất gia, từ bỏ gia đình, sống không gia đình, không phải vì món ăn khất thực … không phải vì sàng tọa … không phải vì dược phẩm trị bệnh mà ta xuất gia, từ bỏ gia đình, sống không gia đình. Nhưng trong khi ta ở tại khu rừng này, các niệm chưa được an trú được an trú … vô thượng an ổn khỏi các ách phược chưa được chứng đạt được chứng đạt”. Này các Tỷ-kheo, Tỷ-kheo ấy chỉ với suy tính này, phải ở lại khu rừng ấy, không được bỏ đi.</p>\n<p><a class='ref sc' id='sc5' href='#sc5'>SC 5</a>Chư Tỷ-kheo, ở đây Tỷ-kheo sống tại một khu rừng nào. Tỷ-kheo sống tại khu rừng này, các niệm chưa được an trú được an trú … vô thượng an ổn khỏi các ách phược chưa được chứng đạt được chứng đạt. Và những vật dụng cần thiết … kiếm được một cách không khó khăn. Chư Tỷ-kheo, Tỷ-kheo ấy cần phải suy nghĩ như sau: “Ta sống tại khu rừng này. Khi ta sống tại khu rừng này, các niệm chưa được an trú được an trú … vô thượng an ổn khỏi các ách phược chưa chứng đạt được chứng đạt, và những vật dụng này cần thiết … kiếm được một cách không khó khăn”. Chư Tỷ-kheo, Tỷ-kheo ấy phải ở lại khu rừng cho đến trọn đời, không được rời bỏ.</p>\n<p><a class='ref sc' id='sc6' href='#sc6'>SC 6</a>Chư Tỷ-kheo, ở đây, Tỷ-kheo sống tại một làng nào …</p>\n<p><a class='ref sc' id='sc7' href='#sc7'>SC 7</a>Chư Tỷ-kheo, ở đây Tỷ-kheo sống tại một thị trấn nào …</p>\n<p><a class='ref sc' id='sc8' href='#sc8'>SC 8</a>Chư Tỷ-kheo, ở đây Tỷ-kheo sống tại một đô thị nào …</p>\n<p><a class='ref sc' id='sc9' href='#sc9'>SC 9</a>Chư Tỷ-kheo, ở đây Tỷ-kheo sống tại một quốc gia nào …</p>\n<p><a class='ref sc' id='sc10' href='#sc10'>SC 10</a>Chư Tỷ-kheo, ở đây Tỷ-kheo sống gần một người nào. Tỷ-kheo sống gần người này, các niệm chưa được an trú không được an trú … không được chứng đạt, và những vật dụng này cần thiết … kiếm được một cách khó khăn. Chư Tỷ-kheo, Tỷ-kheo ấy cần phải suy nghĩ như sau: “Ta sống gần người này. Khi ta sống gần người này, các niệm chưa được an trú không được an trú … không được chứng đạt, và những vật dụng này cần thiết … kiếm được một cách khó khăn”. Chư Tỷ-kheo, vị Tỷ-kheo ấy ngay trong phần đêm ấy hay ngay trong phần ngày ấy, không phải xin phép, cần phải bỏ ngay người ấy mà đi, không cần theo sát người ấy.</p>\n<p><a class='ref sc' id='sc11' href='#sc11'>SC 11</a>Chư Tỷ-kheo, Tỷ-kheo sống gần một người nào. Tỷ-kheo sống gần người ấy, các niệm chưa được an trú không được an trú … không được chứng đạt. Nhưng những vật dụng này cần thiết … kiếm được một cách không khó khăn. Chư Tỷ-kheo, Tỷ-kheo ấy cần phải suy tư như sau: “Ta sống gần người này. Khi ta sống gần người này, các niệm chưa được an trú không được an trú … không được chứng đạt. Nhưng những vật dụng này cần thiết … kiếm được một cách không khó khăn. Nhưng không phải vì y phục mà ta xuất gia, từ bỏ gia đình, sống không gia đình … không phải vì đồ ăn khất thực … không phải vì sàng tọa … không phải vì dược phẩm trị bệnh mà ta xuất gia, từ bỏ gia đình, sống không gia đình. Và khi ta sống gần người này, các niệm chưa được an trú không được an trú … không được chứng đạt”. Chư Tỷ-kheo, Tỷ-kheo ấy, chỉ với ước tính này, cần phải bỏ người ấy mà đi, không có xin phép, không có theo sát.</p>\n<p><a class='ref sc' id='sc12' href='#sc12'>SC 12</a>Chư Tỷ-kheo, ở đây, Tỷ-kheo sống gần một người nào. Tỷ-kheo sống gần người ấy, các niệm chưa được an trú được an trú … được chứng đạt. Những vật dụng này cần thiết … kiếm được một cách khó khăn. Chư Tỷ-kheo, Tỷ-kheo ấy cần phải suy tư như sau: “Ta sống gần người này. Khi ta sống gần người này, các niệm chưa được an trú được an trú … được chứng đạt. Những vật dụng này cần thiết … kiếm được một cách khó khăn. Nhưng không phải vì y phục mà ta xuất gia, từ bỏ gia đình, sống không gia đình … không phải vì đồ ăn khất thực … không phải vì sàng tọa … không phải vì dược phẩm trị bệnh mà ta xuất gia, từ bỏ gia đình, sống không gia đình. Và khi ta sống gần người này, các niệm chưa được an trú được an trú … vô thượng an ổn khỏi các ách phược chưa được chứng đạt được chứng đạt”. Chư Tỷ-kheo, Tỷ-kheo ấy, chỉ với suy tính này, cần phải theo sát người ấy, không được bỏ đi.</p>\n<p><a class='ref sc' id='sc13' href='#sc13'>SC 13</a>Chư Tỷ-kheo, ở đây, Tỷ-kheo sống gần một người nào. Tỷ-kheo sống gần người ấy, các niệm chưa được an trú được an trú, tâm không định tĩnh được định tĩnh, các lậu hoặc chưa được hoàn toàn đoạn trừ được hoàn toàn đoạn trừ, vô thượng an ổn khỏi các ách phược chưa được chứng đạt được chứng đạt, và những vật dụng cần thiết cho đời sống mà một người xuất gia cần phải sắm đủ, như y phục, đồ ăn khất thực, sàng tọa, dược phẩm trị bệnh, những vật dụng này kiếm được một cách không khó khăn. Chư Tỷ-kheo, Tỷ-kheo ấy cần phải suy tư như sau: “Ta sống gần người này. Khi ta sống gần người này, các niệm chưa được an trú được an trú, tâm chưa được định tĩnh được định tĩnh, các lậu hoặc chưa được hoàn toàn đoạn trừ được hoàn toàn đoạn trừ, và vô thượng an ổn, khỏi ách phược chưa được thành đạt được thành đạt. Và những vật dụng cần thiết cho đời sống mà một vị xuất gia cần phải sắm đủ, như y phục, đồ ăn khất thực, sàng tọa, dược phẩm trị bệnh, những vật dụng này kiếm được một cách dễ dàng”. Chư Tỷ-kheo, Tỷ-kheo ấy phải trọn đời theo sát người này, không được bỏ đi, dầu cho có bị xua đuổi.</p>\n<p><a class='ref sc' id='sc14' href='#sc14'>SC 14</a>Thế Tôn thuyết giảng như vậy. Những Tỷ-kheo ấy hoan hỷ, tín thọ lời dạy của Thế Tôn.</p>\n<footer>\n<p><span class='author'>Hòa thượng Thích Minh Châu dịch Việt</span></p>\n<p>Chân thành cám ơn anh HDC và nhóm Phật tử VH đã có thiện tâm gửi tặng ấn bản điện tử.<br>\n(Bình Anson hiệu đính, dựa theo bản Anh ngữ “The Middle Length Discourses of the Buddha”, Tỳ kheo Nanamoli và Tỳ kheo Bodhi dịch, 1995).<br>\n<b>Hiệu đính: 10–06-2004</b></p>\n<p>Prepared for SuttaCentral by <span class='editor'>Blake Walsh</span>.</p>\n</footer>\n</article>\n</body>\n</html>\n"
  },
  "translation": {
    "uid": "mn17",
    "lang": "vi",
    "is_root": false,
    "title": "Kinh Khu rừng",
    "author": "Thích Minh Châu",
    "author_short": "Minh Châu",
    "author_uid": "minh_chau",
    "next": {
      "author_uid": "minh_chau",
      "lang": "vi",
      "name": "The Honey-Cake ",
      "uid": "mn18"
    },
    "previous": {
      "author_uid": "minh_chau",
      "lang": "vi",
      "name": "Emotional Barrenness ",
      "uid": "mn16"
    },
    "text": "<!DOCTYPE html>\n<html>\n<head>\n<meta charset='UTF-8'>\n<meta name='author' content='Thích Minh Châu'>\n<title></title>\n</head>\n<body>\n<article id='mn17' lang='vi'>\n<header>\n<ul>\n<li class='nikaya'>Trung Bộ Kinh</li>\n</ul>\n<h1 class='sutta'>17. Kinh Khu rừng</h1>\n</header>\n<p>Tôi nghe như vầy:</p>\n<p><a class='ref sc' id='sc1' href='#sc1'>SC 1</a>Một thời, Thế Tôn ở <i lang='pli' translate='no'>Sāvatthi</i> (Xá-vệ), tại <i lang='pli' translate='no'>Jetavana</i> (Kỳ-đà Lâm), vườn ông <i lang='pli' translate='no'>Anāthapiṇḍika</i> (Cấp Cô Ðộc). Ở đây, Thế Tôn gọi các Tỷ-kheo: “Này các Tỷ-kheo”. “Bạch Thế Tôn”, các Tỷ-kheo ấy vâng đáp Thế Tôn. Thế Tôn nói như sau: “Chư Tỷ-kheo, Ta sẽ giảng cho các Người pháp môn về khu rừng. Hãy nghe và suy nghiệm kỹ, Ta sẽ giảng”.:” Thưa vâng, bạch Thế Tôn”. Những Tỷ-kheo ấy vâng đáp Thế Tôn. Thế Tôn thuyết giảng như sau</p>\n<p><a class='ref sc' id='sc2' href='#sc2'>SC 2</a>—Chư Tỷ-kheo, ở đây, Tỷ-kheo sống tại một khu rừng nào. Tỷ-kheo sống tại khu rừng này, các niệm chưa được an trú không được an trú, tâm tư chưa được định tĩnh không được định tĩnh, các lậu hoặc chưa được hoàn toàn đoạn trừ không được hoàn toàn đoạn trừ, vô thượng an ổn khỏi các ách phược chưa được chứng đạt không được chứng đạt, và những vật dụng này cần thiết cho đời sống mà một người xuất gia cần phải sắm đủ, như y phục, đồ ăn khất thực, sàng tọa, y dược trị bệnh, những vật dụng này kiếm được một cách khó khăn. Chư Tỷ-kheo, Tỷ-kheo ấy cần phải suy nghĩ: “Ta sống tại khu rừng này. Khi ta sống tại khu rừng này, các niệm chưa được an trú không được an trú, tâm tư chưa được định tĩnh không được định tĩnh, các lậu hoặc chưa được hoàn toàn đoạn trừ không được hoàn toàn đoạn trừ, vô thượng an ổn khỏi các ách phược chưa được chứng đạt không được chứng đạt, và những vật dụng cần thiết cho đời sống mà một vị xuất gia cần phải sắm đủ, như y phục, đồ ăn khất thực, sàng tọa, dược phẩm trị bệnh, những vật dụng này kiếm được một cách khó khăn”. Này các Tỷ-kheo, Tỷ-kheo ấy phải từ bỏ ngôi rừng ấy, không được ở lại, ngay lúc ban ngày hay lúc ban đêm.</p>\n<p><a class='ref sc' id='sc3' href='#sc3'>SC 3</a>Chư Tỷ-kheo, ở đây, Tỷ-kheo sống tại một khu rừng nào. Tỷ-kheo sống tại khu rừng này, các niệm chưa được an trú không được an trú, tâm tư chưa được định tĩnh không được định tĩnh, các lậu hoặc chưa được hoàn toàn đoạn trừ không được hoàn toàn đoạn trừ, vô thượng an ổn khỏi các ách phược chưa được chứng đạt không được chứng đạt, và những vật dụng cần thiết cho đời sống mà một người xuất gia cần phải sắm đủ, như y phục, đồ ăn khất thực, sàng tọa, dược phẩm trị bệnh, những vật dụng này kiếm được một cách không khó khăn. Chư Tỷ-kheo, Tỷ-kheo ấy cần phải suy nghĩ như sau: “Ta sống tại khu rừng này. Khi ta sống tại khu rừng này, các niệm chưa được an trú không được an trú … những vật dụng này kiếm được một cách không khó khăn. Nhưng không phải vì y phục mà ta xuất gia, từ bỏ gia đình sống không gia đình, không phải vì đồ ăn khất thực … không phải vì sàng tọa … không phải vì dược phẩm trị bệnh mà ta xuất gia, từ bỏ gia đình, sống không gia đình. Nhưng trong khi ta ở tại khu rừng này, các niệm chưa được an trú không được an trú … vô thượng an ổn khỏi các ách phược chưa được chứng đạt không được chứng đạt”. Này các Tỷ-kheo, Tỷ-kheo ấy chỉ với suy tính này, phải từ bỏ ngôi rừng ấy, không được ở lại.</p>\n<p><a class='ref sc' id='sc4' href='#sc4'>SC 4</a>Chư Tỷ-kheo, ở đây, Tỷ-kheo sống tại một khu rừng nào. Tỷ-kheo sống tại khu rừng này, các niệm chưa được an trú được an trú, tâm tư chưa được định tĩnh được định tĩnh; các lậu hoặc chưa được hoàn toàn đoạn trừ được hoàn toàn đoạn trừ, vô thượng an ổn khỏi các ách phược chưa được chứng đạt được chứng đạt, nhưng những vật dụng cần thiết cho đời sống một người xuất gia cần phải sắm đủ, như y phục, đồ ăn khất thực, sàng tọa, dược phẩm trị bệnh, những vật này kiếm được một cách khó khăn. Chư Tỷ-kheo, Tỷ-kheo ấy cần phải suy nghĩ như sau: “Ta sống tại khu rừng này. Khi ta sống tại khu rừng này, các niệm chưa được an trú được an trú … vô thượng an ổn khỏi các ách phược chưa được chứng đạt được chứng đạt … những vật dụng này kiếm được một cách khó khăn. Nhưng không phải vì y phục mà ta xuất gia, từ bỏ gia đình, sống không gia đình, không phải vì món ăn khất thực … không phải vì sàng tọa … không phải vì dược phẩm trị bệnh mà ta xuất gia, từ bỏ gia đình, sống không gia đình. Nhưng trong khi ta ở tại khu rừng này, các niệm chưa được an trú được an trú … vô thượng an ổn khỏi các ách phược chưa được chứng đạt được chứng đạt”. Này các Tỷ-kheo, Tỷ-kheo ấy chỉ với suy tính này, phải ở lại khu rừng ấy, không được bỏ đi.</p>\n<p><a class='ref sc' id='sc5' href='#sc5'>SC 5</a>Chư Tỷ-kheo, ở đây Tỷ-kheo sống tại một khu rừng nào. Tỷ-kheo sống tại khu rừng này, các niệm chưa được an trú được an trú … vô thượng an ổn khỏi các ách phược chưa được chứng đạt được chứng đạt. Và những vật dụng cần thiết … kiếm được một cách không khó khăn. Chư Tỷ-kheo, Tỷ-kheo ấy cần phải suy nghĩ như sau: “Ta sống tại khu rừng này. Khi ta sống tại khu rừng này, các niệm chưa được an trú được an trú … vô thượng an ổn khỏi các ách phược chưa chứng đạt được chứng đạt, và những vật dụng này cần thiết … kiếm được một cách không khó khăn”. Chư Tỷ-kheo, Tỷ-kheo ấy phải ở lại khu rừng cho đến trọn đời, không được rời bỏ.</p>\n<p><a class='ref sc' id='sc6' href='#sc6'>SC 6</a>Chư Tỷ-kheo, ở đây, Tỷ-kheo sống tại một làng nào …</p>\n<p><a class='ref sc' id='sc7' href='#sc7'>SC 7</a>Chư Tỷ-kheo, ở đây Tỷ-kheo sống tại một thị trấn nào …</p>\n<p><a class='ref sc' id='sc8' href='#sc8'>SC 8</a>Chư Tỷ-kheo, ở đây Tỷ-kheo sống tại một đô thị nào …</p>\n<p><a class='ref sc' id='sc9' href='#sc9'>SC 9</a>Chư Tỷ-kheo, ở đây Tỷ-kheo sống tại một quốc gia nào …</p>\n<p><a class='ref sc' id='sc10' href='#sc10'>SC 10</a>Chư Tỷ-kheo, ở đây Tỷ-kheo sống gần một người nào. Tỷ-kheo sống gần người này, các niệm chưa được an trú không được an trú … không được chứng đạt, và những vật dụng này cần thiết … kiếm được một cách khó khăn. Chư Tỷ-kheo, Tỷ-kheo ấy cần phải suy nghĩ như sau: “Ta sống gần người này. Khi ta sống gần người này, các niệm chưa được an trú không được an trú … không được chứng đạt, và những vật dụng này cần thiết … kiếm được một cách khó khăn”. Chư Tỷ-kheo, vị Tỷ-kheo ấy ngay trong phần đêm ấy hay ngay trong phần ngày ấy, không phải xin phép, cần phải bỏ ngay người ấy mà đi, không cần theo sát người ấy.</p>\n<p><a class='ref sc' id='sc11' href='#sc11'>SC 11</a>Chư Tỷ-kheo, Tỷ-kheo sống gần một người nào. Tỷ-kheo sống gần người ấy, các niệm chưa được an trú không được an trú … không được chứng đạt. Nhưng những vật dụng này cần thiết … kiếm được một cách không khó khăn. Chư Tỷ-kheo, Tỷ-kheo ấy cần phải suy tư như sau: “Ta sống gần người này. Khi ta sống gần người này, các niệm chưa được an trú không được an trú … không được chứng đạt. Nhưng những vật dụng này cần thiết … kiếm được một cách không khó khăn. Nhưng không phải vì y phục mà ta xuất gia, từ bỏ gia đình, sống không gia đình … không phải vì đồ ăn khất thực … không phải vì sàng tọa … không phải vì dược phẩm trị bệnh mà ta xuất gia, từ bỏ gia đình, sống không gia đình. Và khi ta sống gần người này, các niệm chưa được an trú không được an trú … không được chứng đạt”. Chư Tỷ-kheo, Tỷ-kheo ấy, chỉ với ước tính này, cần phải bỏ người ấy mà đi, không có xin phép, không có theo sát.</p>\n<p><a class='ref sc' id='sc12' href='#sc12'>SC 12</a>Chư Tỷ-kheo, ở đây, Tỷ-kheo sống gần một người nào. Tỷ-kheo sống gần người ấy, các niệm chưa được an trú được an trú … được chứng đạt. Những vật dụng này cần thiết … kiếm được một cách khó khăn. Chư Tỷ-kheo, Tỷ-kheo ấy cần phải suy tư như sau: “Ta sống gần người này. Khi ta sống gần người này, các niệm chưa được an trú được an trú … được chứng đạt. Những vật dụng này cần thiết … kiếm được một cách khó khăn. Nhưng không phải vì y phục mà ta xuất gia, từ bỏ gia đình, sống không gia đình … không phải vì đồ ăn khất thực … không phải vì sàng tọa … không phải vì dược phẩm trị bệnh mà ta xuất gia, từ bỏ gia đình, sống không gia đình. Và khi ta sống gần người này, các niệm chưa được an trú được an trú … vô thượng an ổn khỏi các ách phược chưa được chứng đạt được chứng đạt”. Chư Tỷ-kheo, Tỷ-kheo ấy, chỉ với suy tính này, cần phải theo sát người ấy, không được bỏ đi.</p>\n<p><a class='ref sc' id='sc13' href='#sc13'>SC 13</a>Chư Tỷ-kheo, ở đây, Tỷ-kheo sống gần một người nào. Tỷ-kheo sống gần người ấy, các niệm chưa được an trú được an trú, tâm không định tĩnh được định tĩnh, các lậu hoặc chưa được hoàn toàn đoạn trừ được hoàn toàn đoạn trừ, vô thượng an ổn khỏi các ách phược chưa được chứng đạt được chứng đạt, và những vật dụng cần thiết cho đời sống mà một người xuất gia cần phải sắm đủ, như y phục, đồ ăn khất thực, sàng tọa, dược phẩm trị bệnh, những vật dụng này kiếm được một cách không khó khăn. Chư Tỷ-kheo, Tỷ-kheo ấy cần phải suy tư như sau: “Ta sống gần người này. Khi ta sống gần người này, các niệm chưa được an trú được an trú, tâm chưa được định tĩnh được định tĩnh, các lậu hoặc chưa được hoàn toàn đoạn trừ được hoàn toàn đoạn trừ, và vô thượng an ổn, khỏi ách phược chưa được thành đạt được thành đạt. Và những vật dụng cần thiết cho đời sống mà một vị xuất gia cần phải sắm đủ, như y phục, đồ ăn khất thực, sàng tọa, dược phẩm trị bệnh, những vật dụng này kiếm được một cách dễ dàng”. Chư Tỷ-kheo, Tỷ-kheo ấy phải trọn đời theo sát người này, không được bỏ đi, dầu cho có bị xua đuổi.</p>\n<p><a class='ref sc' id='sc14' href='#sc14'>SC 14</a>Thế Tôn thuyết giảng như vậy. Những Tỷ-kheo ấy hoan hỷ, tín thọ lời dạy của Thế Tôn.</p>\n<footer>\n<p><span class='author'>Hòa thượng Thích Minh Châu dịch Việt</span></p>\n<p>Chân thành cám ơn anh HDC và nhóm Phật tử VH đã có thiện tâm gửi tặng ấn bản điện tử.<br>\n(Bình Anson hiệu đính, dựa theo bản Anh ngữ “The Middle Length Discourses of the Buddha”, Tỳ kheo Nanamoli và Tỳ kheo Bodhi dịch, 1995).<br>\n<b>Hiệu đính: 10–06-2004</b></p>\n<p>Prepared for SuttaCentral by <span class='editor'>Blake Walsh</span>.</p>\n</footer>\n</article>\n</body>\n</html>\n"
  },
  "segmented": false,
  "suttaplex": {
    "acronym": "MN 17",
    "volpages": " PTS 1.105, PTS 1.106, PTS 1.107, PTS 1.108",
    "alt_volpages": null,
    "uid": "mn17",
    "blurb": "While living in the wilderness is great, not everyone is ready for it. The Buddha encourages meditators to reflect on whether one’s environment is genuinely supporting their meditation practice, and if not, to leave.",
    "difficulty": 1,
    "original_title": "Vanapatthasutta",
    "root_lang": "pli",
    "root_lang_name": "Pāli",
    "type": "leaf",
    "from": null,
    "translated_title": "Kinh Khu rừng",
    "translations": [
      {
        "lang": "de",
        "lang_name": "Deutsch",
        "is_root": false,
        "author": "Sabbamitta",
        "author_short": "sabbamitta",
        "author_uid": "sabbamitta",
        "publication_date": "2019",
        "id": "mn17_translation-de-sabbamitta",
        "segmented": true,
        "title": "Urwalddickichte ",
        "volpage": null,
        "has_comment": false
      },
      {
        "lang": "en",
        "lang_name": "English",
        "is_root": false,
        "author": "Bhikkhu Sujato",
        "author_short": "sujato",
        "author_uid": "sujato",
        "publication_date": "2018",
        "id": "mn17_translation-en-sujato",
        "segmented": true,
        "title": "Jungle Thickets ",
        "volpage": null,
        "has_comment": true
      },
      {
        "lang": "it",
        "lang_name": "Italiano",
        "is_root": false,
        "author": "Giovanni Zappa",
        "author_short": "giovannizappa",
        "author_uid": "giovannizappa",
        "publication_date": "2025",
        "id": "mn17_translation-it-giovannizappa",
        "segmented": true,
        "title": "Il discorso sui luoghi nella giungla ",
        "volpage": null,
        "has_comment": false
      },
      {
        "lang": "pli",
        "lang_name": "Pāli",
        "is_root": true,
        "author": "Mahāsaṅgīti Tipiṭaka Buddhavasse 2500",
        "author_short": "ms",
        "author_uid": "ms",
        "publication_date": null,
        "id": "mn17_root-pli-ms",
        "segmented": true,
        "title": null,
        "volpage": null,
        "has_comment": false
      },
      {
        "lang": "ru",
        "lang_name": "Русский",
        "is_root": false,
        "author": "SV theravada.ru",
        "author_short": "sv",
        "author_uid": "sv",
        "publication_date": "2023",
        "id": "mn17_translation-ru-sv",
        "segmented": true,
        "title": "Лесная чаща ",
        "volpage": null,
        "has_comment": false
      },
      {
        "lang": "sr",
        "lang_name": "Srpski",
        "is_root": false,
        "author": "Branislav Kovačević",
        "author_short": "brankokovacevic",
        "author_uid": "brankokovacevic",
        "publication_date": "2023",
        "id": "mn17_translation-sr-brankokovacevic",
        "segmented": true,
        "title": "Gusta džungla ",
        "volpage": null,
        "has_comment": false
      },
      {
        "lang": "bn",
        "lang_name": "বাংলা",
        "is_root": false,
        "author": "ড. বেণীমাধব বড়ুয়া",
        "author_short": "বড়ুয়া",
        "author_uid": "barua",
        "publication_date": null,
        "id": "bn_mn17_barua",
        "segmented": false,
        "volpage": null,
        "has_comment": false
      },
      {
        "lang": "cs",
        "lang_name": "Čeština",
        "is_root": false,
        "author": "Štěpán Chromovský",
        "author_short": "Chromovský",
        "author_uid": "chromovsky",
        "publication_date": null,
        "id": "cs_mn17_chromovsky",
        "segmented": false,
        "volpage": null,
        "has_comment": false
      },
      {
        "lang": "de",
        "lang_name": "Deutsch",
        "is_root": false,
        "author": "Mettiko Bhikkhu",
        "author_short": "Mettiko",
        "author_uid": "mettiko",
        "publication_date": "2001",
        "id": "de_mn17_mettiko",
        "segmented": false,
        "volpage": null,
        "has_comment": false
      },
      {
        "lang": "en",
        "lang_name": "English",
        "is_root": false,
        "author": "Suddhāso Bhikkhu",
        "author_short": "Suddhāso",
        "author_uid": "suddhaso",
        "publication_date": "2018",
        "id": "en_mn17_suddhaso",
        "segmented": false,
        "volpage": null,
        "has_comment": false
      },
      {
        "lang": "en",
        "lang_name": "English",
        "is_root": false,
        "author": "I.B. Horner",
        "author_short": "Horner",
        "author_uid": "horner",
        "publication_date": "1954–9",
        "id": "en_mn17_horner",
        "segmented": false,
        "volpage": null,
        "has_comment": false
      },
      {
        "lang": "es",
        "lang_name": "Español",
        "is_root": false,
        "author": "Anton P. Baron",
        "author_short": "Baron",
        "author_uid": "baron",
        "publication_date": null,
        "id": "es_mn17_baron",
        "segmented": false,
        "volpage": null,
        "has_comment": false
      },
      {
        "lang": "fr",
        "lang_name": "Français",
        "is_root": false,
        "author": "Christian Maës",
        "author_short": "Maës",
        "author_uid": "maes",
        "publication_date": null,
        "id": "fr_mn17_maes",
        "segmented": false,
        "volpage": null,
        "has_comment": false
      },
      {
        "lang": "fr",
        "lang_name": "Français",
        "is_root": false,
        "author": "Môhan Wijayaratna",
        "author_short": "wijayaratna",
        "author_uid": "wijayaratna",
        "publication_date": "2010",
        "id": "fr_mn17_wijayaratna",
        "segmented": false,
        "volpage": null,
        "has_comment": false
      },
      {
        "lang": "fr",
        "lang_name": "Français",
        "is_root": false,
        "author": "buddha-vacana.org",
        "author_short": "BVO",
        "author_uid": "buddhavacanaorg",
        "publication_date": null,
        "id": "fr_mn17_buddhavacanaorg",
        "segmented": false,
        "volpage": null,
        "has_comment": false
      },
      {
        "lang": "hi",
        "lang_name": "हिन्दी",
        "is_root": false,
        "author": "Rahul Sankrityayan",
        "author_short": "Sankrityayan",
        "author_uid": "sankrityayan",
        "publication_date": "1933",
        "id": "hi_mn17_sankrityayan",
        "segmented": false,
        "volpage": null,
        "has_comment": false
      },
      {
        "lang": "hu",
        "lang_name": "Magyar",
        "is_root": false,
        "author": "Vekerdi József",
        "author_short": "Vekerdi",
        "author_uid": "vekerdi",
        "publication_date": "1989",
        "id": "hu_mn17_vekerdi",
        "segmented": false,
        "volpage": null,
        "has_comment": false
      },
      {
        "lang": "id",
        "lang_name": "Bahasa Indonesia",
        "is_root": false,
        "author": "Indra Anggara",
        "author_short": "Anggara",
        "author_uid": "anggara",
        "publication_date": null,
        "id": "id_mn17_anggara",
        "segmented": false,
        "volpage": null,
        "has_comment": false
      },
      {
        "lang": "it",
        "lang_name": "Italiano",
        "is_root": false,
        "author": "De Lorenzo, Pier Antonio Morniroli, Enrico Federici",
        "author_short": "Lorenzo …",
        "author_uid": "lorenzo-morniroli-federici",
        "publication_date": "2007",
        "id": "it_mn17_lorenzo-morniroli-federici",
        "segmented": false,
        "volpage": null,
        "has_comment": false
      },
      {
        "lang": "jpn",
        "lang_name": "日本語",
        "is_root": false,
        "author": "関西パーリ語実習会",
        "author_short": "関西パーリ語実習会",
        "author_uid": "kansai",
        "publication_date": "2023",
        "id": "jpn_mn17_kansai",
        "segmented": false,
        "volpage": null,
        "has_comment": false
      },
      {
        "lang": "kan",
        "lang_name": "ಕನ್ನಡ",
        "is_root": false,
        "author": "Dr. J. Srinivas Murthy",
        "author_short": "murthy",
        "author_uid": "murthy",
        "publication_date": "2012",
        "id": "kan_mn17_murthy",
        "segmented": false,
        "volpage": null,
        "has_comment": false
      },
      {
        "lang": "my",
        "lang_name": "မြန်မာဘာသာ",
        "is_root": false,
        "author": "Pitaka Myanmar Translation",
        "author_short": "PMT",
        "author_uid": "pmt",
        "publication_date": null,
        "id": "my_mn17_pmt",
        "segmented": false,
        "volpage": null,
        "has_comment": false
      },
      {
        "lang": "no",
        "lang_name": "Norsk",
        "is_root": false,
        "author": "Kåre A. Lie",
        "author_short": "Lie",
        "author_uid": "lie",
        "publication_date": "2013",
        "id": "no_mn17_lie",
        "segmented": false,
        "volpage": null,
        "has_comment": false
      },
      {
        "lang": "pt",
        "lang_name": "Português",
        "is_root": false,
        "author": "Michael Beisert",
        "author_short": "Beisert",
        "author_uid": "beisert",
        "publication_date": "2006",
        "id": "pt_mn17_beisert",
        "segmented": false,
        "volpage": null,
        "has_comment": false
      },
      {
        "lang": "ru",
        "lang_name": "Русский",
        "is_root": false,
        "author": "баян купи-ка",
        "author_short": "купи-ка",
        "author_uid": "kupi-ka",
        "publication_date": null,
        "id": "ru_mn17_kupi-ka",
        "segmented": false,
        "volpage": null,
        "has_comment": false
      },
      {
        "lang": "ru",
        "lang_name": "Русский",
        "is_root": false,
        "author": "SV",
        "author_short": "SV",
        "author_uid": "sv",
        "publication_date": "2013",
        "id": "ru_mn17_sv",
        "segmented": false,
        "volpage": null,
        "has_comment": false
      },
      {
        "lang": "si",
        "lang_name": "සිංහල",
        "is_root": false,
        "author": "A.P. de Zoysa",
        "author_short": "Zoysa",
        "author_uid": "zoysa",
        "publication_date": null,
        "id": "si_mn17_zoysa",
        "segmented": false,
        "volpage": null,
        "has_comment": false
      },
      {
        "lang": "sl",
        "lang_name": "Slovenščina",
        "is_root": false,
        "author": "Bojan Božič",
        "author_short": "Božič",
        "author_uid": "bojan",
        "publication_date": "2023",
        "id": "sl_mn17_bojan",
        "segmented": false,
        "volpage": null,
        "has_comment": false
      },
      {
        "lang": "sr",
        "lang_name": "Srpski",
        "is_root": false,
        "author": "Branislav Kovačević",
        "author_short": "Kovačević",
        "author_uid": "kovacevic",
        "publication_date": "2014",
        "id": "sr_mn17_kovacevic",
        "segmented": false,
        "volpage": null,
        "has_comment": false
      },
      {
        "lang": "th",
        "lang_name": "ไทย",
        "is_root": false,
        "author": "Siam Rath",
        "author_short": "Siam Rath",
        "author_uid": "siam_rath",
        "publication_date": null,
        "id": "th_mn17_siam_rath",
        "segmented": false,
        "volpage": null,
        "has_comment": false
      },
      {
        "author": "Thích Minh Châu",
        "author_short": "Minh Châu",
        "author_uid": "minh_chau",
        "has_comment": false,
        "id": "vi_mn17_minh_chau",
        "is_root": false,
        "lang": "vi",
        "lang_name": "Tiếng Việt",
        "publication_date": null,
        "segmented": false,
        "volpage": null,
        "title": "Kinh Khu rừng"
      },
      {
        "lang": "zh",
        "lang_name": "汉语",
        "is_root": false,
        "author": "莊春江",
        "author_short": "莊春江",
        "author_uid": "zhuang",
        "publication_date": null,
        "id": "zh_mn17_zhuang",
        "segmented": false,
        "volpage": null,
        "has_comment": false
      }
    ],
    "parallel_count": 4,
    "biblio": null,
    "priority_author_uid": null,
    "verseNo": "bj10.264, dr12.192, ms9M_689, msdiv190, ndp9.141, nya1, sya12.212, vri12.150,nya2,cck12.199, csp1ed9.150, csp2ed9.150, ms9M_690, msdiv191, nya3, pts-vp-pli1.105, sya12.213,bj10.266, cck12.200, dr12.193, ms9M_691, msdiv192, ndp9.142, nya4, sya12.214, vri12.151,cck12.201, csp1ed9.151, csp2ed9.151, dr12.194, ms9M_692, msdiv193, ndp9.143, nya5, pts-vp-pli1.106, sya12.215,bj10.268, cck12.202, csp1ed9.152, csp2ed9.152, ms9M_693, msdiv194, nya6, vri12.152,cck12.203, dr12.195, ms9M_694, msdiv195, ndp9.144, nya7-22, sya12.216,nya23,bj10.270, cck12.204, csp1ed9.153, csp2ed9.153, dr12.196, ms9M_695, msdiv196, nya24, pts-vp-pli1.107, sya12.217, vri12.153,cck12.205, dr12.197, ms9M_696, msdiv197, ndp9.145, nya25, sya12.218, vri12.154,bj10.272, csp1ed9.154, csp2ed9.154, dr12.198, ms9M_697, msdiv198, nya26, pts-vp-pli1.108, sya12.219,ms9M_698",
    "previous": {
      "name": null,
      "uid": null
    },
    "next": {
      "name": null,
      "uid": null
    }
  },
  "bilara_root_text": {
    "uid": "mn17",
    "author": "Mahāsaṅgīti Tipiṭaka Buddhavasse 2500",
    "author_short": "ms",
    "author_uid": "ms",
    "lang": "pli",
    "title": "Vanapatthasutta",
    "previous": {
      "author_uid": "ms",
      "lang": "pli",
      "name": null,
      "uid": null
    },
    "next": {
      "author_uid": "ms",
      "lang": "pli",
      "name": null,
      "uid": null
    }
  },
  "bilara_translated_text": null,
  "candidate_authors": [
    "sujato",
    "suddhaso",
    "horner"
  ]
}